utils_flask_sqla/__init__.py
utils_flask_sqla/commands.py
utils_flask_sqla/db.py
utils_flask_sqla/errors.py
utils_flask_sqla/generic.py
utils_flask_sqla/models.py
utils_flask_sqla/response.py
utils_flask_sqla/schema.py
utils_flask_sqla/serializers.py
utils_flask_sqla/utils.py
utils_flask_sqla/migrations/__init__.py
utils_flask_sqla/migrations/utils.py
utils_flask_sqla/migrations/versions/3842a6d800a0_sql_utils.py
utils_flask_sqla/migrations/versions/__init__.py
utils_flask_sqla/migrations/versions/ba207b468e31_create_fr_numeric_collation.py
utils_flask_sqla/tests/__init__.py
utils_flask_sqla/tests/fixtures.py
utils_flask_sqla/tests/plugin.py
utils_flask_sqla/tests/test_ordered.py
utils_flask_sqla/tests/test_qfilter.py
utils_flask_sqla/tests/test_schema.py
utils_flask_sqla/tests/test_serializers.py
utils_flask_sqla/tests/test_temporary_transaction.py
utils_flask_sqla/tests/utils.py
utils_flask_sqlalchemy-0.4.3.dist-info/licenses/LICENSE
utils_flask_sqlalchemy-0.4.3.dist-info/METADATA
utils_flask_sqlalchemy-0.4.3.dist-info/WHEEL
utils_flask_sqlalchemy-0.4.3.dist-info/entry_points.txt
utils_flask_sqlalchemy-0.4.3.dist-info/top_level.txt
utils_flask_sqlalchemy-0.4.3.dist-info/RECORD
