Metadata-Version: 2.4
Name: utils-flask-sqlalchemy
Version: 0.4.3
Summary: Python lib of tools for Flask and SQLAlchemy
Home-page: https://github.com/PnX-SI/Utils-Flask-SQLAlchemy
Maintainer: Parcs nationaux des Écrins et des Cévennes
Maintainer-email: geonature@ecrins-parcnational.fr
Classifier: Development Status :: 1 - Planning
Classifier: Intended Audience :: Developers
Classifier: Natural Language :: English
Classifier: Programming Language :: Python :: 3
Classifier: License :: OSI Approved :: GNU Affero General Public License v3
Classifier: Operating System :: OS Independent
License-File: LICENSE
Requires-Dist: flask
Requires-Dist: flask-sqlalchemy
Requires-Dist: flask-migrate
Requires-Dist: marshmallow
Requires-Dist: python-dateutil
Requires-Dist: sqlalchemy<2
Provides-Extra: tests
Requires-Dist: pytest; extra == "tests"
Requires-Dist: geoalchemy2; extra == "tests"
Requires-Dist: shapely; extra == "tests"
Requires-Dist: jsonschema; extra == "tests"
Requires-Dist: flask-marshmallow; extra == "tests"
Requires-Dist: marshmallow-sqlalchemy; extra == "tests"
Dynamic: classifier
Dynamic: description
Dynamic: description-content-type
Dynamic: home-page
Dynamic: license-file
Dynamic: maintainer
Dynamic: maintainer-email
Dynamic: provides-extra
Dynamic: requires-dist
Dynamic: summary
